fast_pony_crud/__init__.py
fast_pony_crud/api_delete.py
fast_pony_crud/api_get.py
fast_pony_crud/api_model.py
fast_pony_crud/api_post.py
fast_pony_crud/api_put.py
fast_pony_crud/security.py
fast_pony_crud/table_crud.py
fast_pony_crud-0.0.8.dist-info/LICENCE
fast_pony_crud-0.0.8.dist-info/METADATA
fast_pony_crud-0.0.8.dist-info/WHEEL
fast_pony_crud-0.0.8.dist-info/top_level.txt
fast_pony_crud-0.0.8.dist-info/RECORD
