Metadata-Version: 2.1
Name: fast-pony-crud
Version: 0.0.8
Summary: Tool for creating crud routes from pony database object
Home-page: https://github.com/juanborbon93/fast_pony_crud
Author: MakeHax
Author-email: info@makehax.com
License: UNKNOWN
Platform: UNKNOWN
Classifier: Programming Language :: Python :: 3
Classifier: Operating System :: OS Independent
Requires-Python: >=3.7
License-File: LICENCE
Requires-Dist: pony (>=0.7.14)
Requires-Dist: pydantic (>=1.8)
Requires-Dist: fastapi (>=0.63.0)
